pyexcel_text/__init__.py
pyexcel_text/jsonp.py
pyexcel_text/jsonr.py
pyexcel_text/ndjsonp.py
pyexcel_text/textr.py
pyexcel_text-0.2.7.1.dist-info/DESCRIPTION.rst
pyexcel_text-0.2.7.1.dist-info/METADATA
pyexcel_text-0.2.7.1.dist-info/RECORD
pyexcel_text-0.2.7.1.dist-info/WHEEL
pyexcel_text-0.2.7.1.dist-info/metadata.json
pyexcel_text-0.2.7.1.dist-info/top_level.txt
