Metadata-Version: 2.0
Name: pyexcel-text
Version: 0.2.7.1
Summary: A plugin to pyexcel and provides the capability to present and write data in text formats
Home-page: https://github.com/pyexcel/pyexcel-text
Author: C.W.
Author-email: wangc_2011@hotmail.com
License: New BSD
Download-URL: https://github.com/pyexcel/pyexcel-text/archive/0.2.7.1.tar.gz
Keywords: plain,simple,grid,pipe,orgtbl,rst,mediawiki,latex,latex_booktabs,html,jsonpython
Platform: UNKNOWN
Classifier: Topic :: Office/Business
Classifier: Topic :: Utilities
Classifier: Topic :: Software Development :: Libraries
Classifier: Programming Language :: Python
Classifier: License :: OSI Approved :: BSD License
Classifier: Intended Audience :: Developers
Classifier: Programming Language :: Python :: 2.6
Classifier: Programming Language :: Python :: 2.7
Classifier: Programming Language :: Python :: 3.3
Classifier: Programming Language :: Python :: 3.4
Classifier: Programming Language :: Python :: 3.5
Classifier: Programming Language :: Python :: 3.6
Requires-Dist: pyexcel (>=0.5.0)
Requires-Dist: tabulate (>=0.7.4)
